Linko/__init__.py
linko-0.0.13.dist-info/LICENSE
linko-0.0.13.dist-info/METADATA
linko-0.0.13.dist-info/WHEEL
linko-0.0.13.dist-info/top_level.txt
linko-0.0.13.dist-info/RECORD
