Metadata-Version: 2.1
Name: linko
Version: 0.0.13
Summary: Connect Python and HTML to pass varius Methods.
Home-page: https://github.com/monnapse/linko
Author: Monnapse
Author-email: monnapse@gmail.com
Project-URL: Bug Tracker, https://github.com/monnapse/linko/issues
Classifier: Programming Language :: Python :: 3
Classifier: License :: OSI Approved :: MIT License
Classifier: Operating System :: OS Independent
Requires-Python: >=3.7
License-File: LICENSE
